<?xml version="1.0" encoding="utf-8"?>
<Data>
  <Add Id="0f22ff42-49da-46b7-a512-2c386e83aabd" Title="HeelsHeight" FieldName="HeelsHeight" FacetType="SingleSelect" SortWeight="1.50" MaxCollapsedValueCount="0" DependsOn=""  IsDisplayed="True" PromotedValues="" />
  <Add Id="28baa53f-88c3-441f-82de-83f0dc1d5db3" Title="Brand" FieldName="Brand" FacetType="MultiSelect" SortWeight="0.00" MaxCollapsedValueCount="5" MaxExpendedValueCount="20" DependsOn=""  IsDisplayed="True" PromotedValues="" />
  <Add Id="2d37371a-d76e-4370-9ceb-49a917773d15" Title="ShirtType" FieldName="ShirtType" FacetType="MultiSelect" SortWeight="1.50" MaxCollapsedValueCount="5" DependsOn="" IsDisplayed="True" PromotedValues="" />
  <Add Id="5d78f16f-9913-4cf2-9ed8-6423bf6aa6eb" Title="CategoryLevel1_Facet" FieldName="CategoryLevel1_Facet" FacetType="SingleSelect" SortWeight="-1.00" MaxCollapsedValueCount="5" DependsOn=""  IsDisplayed="True" PromotedValues="" />
  <Add Id="71d503ca-f5df-43ac-a9f7-d0aa5beb69c2" Title="CategoryLevel3_Facet" FieldName="CategoryLevel3_Facet" FacetType="SingleSelect" SortWeight="-1.10" MaxCollapsedValueCount="5" DependsOn="a1b99f20-bf96-4395-85e2-7f29ff0a70be"  IsDisplayed="True" PromotedValues="" />
  <Add Id="7248c1c2-2c40-41a3-ae01-8ef1420562d5" Title="SeasonWear" FieldName="SeasonWear" FacetType="MultiSelect" SortWeight="1.00" MaxCollapsedValueCount="5" DependsOn=""  IsDisplayed="True" PromotedValues="" />
  <Add Id="a1b99f20-bf96-4395-85e2-7f29ff0a70be" Title="CategoryLevel2_Facet" FieldName="CategoryLevel2_Facet" FacetType="SingleSelect" SortWeight="-1.00" MaxCollapsedValueCount="5" MaxExpendedValueCount="1" DependsOn="5d78f16f-9913-4cf2-9ed8-6423bf6aa6eb"  IsDisplayed="True" PromotedValues="" />
  <Add Id="ba3ebc5a-9afa-4a26-83ae-55c18fb2a7c3" Title="CurrentPrice" FieldName="CurrentPrice" FacetType="Range" SortWeight="2.00" MaxCollapsedValueCount="5" DependsOn=""  IsDisplayed="True" PromotedValues="" />
  <Add Id="d0eb63fa-9860-4744-b7b4-18c8570733de" Title="ShoeType" FieldName="ShoeType" FacetType="SingleSelect" SortWeight="1.50" MaxCollapsedValueCount="5" DependsOn=""  IsDisplayed="True" PromotedValues="" />
</Data>